deebeebros/__init__.py
deebeebros/base_test.py
deebeebros/prompt_helpers.py
deebeebros-0.0.8.dist-info/licenses/LICENSE
deebeebros-0.0.8.dist-info/METADATA
deebeebros-0.0.8.dist-info/WHEEL
deebeebros-0.0.8.dist-info/entry_points.txt
deebeebros-0.0.8.dist-info/top_level.txt
deebeebros-0.0.8.dist-info/RECORD
