Metadata-Version: 2.4
Name: deebeebros
Version: 0.0.8
Summary: DeeBeeBros.com makes you dig coding
Author-email: "Victor G.B. Peters" <victor@jeex.eu>
Project-URL: Homepage, https://github.com/jeex/deebeebros
Project-URL: Issues, https://github.com/jeex/deebeebros/issues
Classifier: Programming Language :: Python :: 3
Classifier: License :: OSI Approved :: MIT License
Classifier: Operating System :: OS Independent
Requires-Python: >=3.11
License-File: LICENSE
Requires-Dist: PyYAML
Requires-Dist: pytz
Requires-Dist: certifi
Requires-Dist: requests
Requires-Dist: pyperclip
Requires-Dist: colorama
Requires-Dist: platformdirs
Dynamic: license-file
